Text_Classifier_based_Openai_Community_gpt2/__init__.py
Text_Classifier_based_Openai_Community_gpt2/text_classification_model.py
Text_Classifier_based_Openai_Community_gpt2-0.1.3.dist-info/LICENSE
Text_Classifier_based_Openai_Community_gpt2-0.1.3.dist-info/METADATA
Text_Classifier_based_Openai_Community_gpt2-0.1.3.dist-info/WHEEL
Text_Classifier_based_Openai_Community_gpt2-0.1.3.dist-info/top_level.txt
Text_Classifier_based_Openai_Community_gpt2-0.1.3.dist-info/RECORD
