Metadata-Version: 2.1
Name: Text-Classifier-based-Openai-Community-gpt2
Version: 0.1.3
Summary: A library that leverages the pre-trained openai-community/gpt2 model for multilingual text classification (French, German, and English), providing straightforward fine-tuning capabilities for sequence classification tasks.
Home-page: https://github.com/mehrdadalmasi2020/Text_Classifier_based_Openai_Community_gpt2
Author: Mehrdad ALMASI, Demival VASQUES FILHO, Gabor Mihaly TOTH)
Author-email: mehrdad.al.2023@gmail.com, demival.vasques@uni.lu, gabor.toth@uni.lu
Classifier: Programming Language :: Python :: 3
Classifier: License :: OSI Approved :: MIT License
Classifier: Operating System :: OS Independent
Requires-Python: >=3.6
License-File: LICENSE
Requires-Dist: transformers (<5.0.0,>=4.20.0)
Requires-Dist: tokenizers (<0.14.0,>=0.10.0)
Requires-Dist: torch (<2.0.0,>=1.7.0)
Requires-Dist: pandas (>=1.1.0)
Requires-Dist: scikit-learn (>=1.0)
Requires-Dist: numpy (<1.24.0,>=1.19.0)
